Metadata-Version: 1.0
Name: clearai
Version: 1.0.0
Summary: ClearAI is a library with which you can create a neural network in a few lines.
Home-page: UNKNOWN
Author: NullGuy / Bogdan Tanov
Author-email: playmister00@gmail.com
License: UNKNOWN
Platform: UNKNOWN
